MANIFEST.in
README.rst
setup.py
django_ndator.egg-info/PKG-INFO
django_ndator.egg-info/SOURCES.txt
django_ndator.egg-info/dependency_links.txt
django_ndator.egg-info/not-zip-safe
django_ndator.egg-info/requires.txt
django_ndator.egg-info/top_level.txt
ndator/__init__.py
ndator/management/__init__.py
ndator/management/commands/__init__.py
ndator/management/commands/nda.py
ndator/nda/__init__.py
ndator/nda/fields.py
ndator/nda/finder.py
ndator/nda/models.py
ndator/texts/login.txt
ndator/texts/lorem.txt
ndator/texts/names.txt