Metadata-Version: 1.0
Name: django-ndator
Version: 0.1.7
Summary: Django models obfuscator
Home-page: http://github.com/zubchick/django-ndator
Author: Nikita Zubkov
Author-email: zubchick@gmail.com
License: New BSD License
Platform: UNKNOWN
Classifier: Framework :: Django
Classifier: Environment :: Web Environment
Classifier: Intended Audience :: Developers
Classifier: License :: OSI Approved :: BSD License
Classifier: Programming Language :: Python
Classifier: Operating System :: OS Independent
Classifier: Topic :: Software Development
